dagster_dora/__init__.py
dagster_dora/aws/__init__.py
dagster_dora/aws/assets.py
dagster_dora/aws/evaluators.py
dagster_dora/aws/operators.py
dagster_dora/aws/resources.py
dagster_dora-0.1.0.dist-info/LICENSE
dagster_dora-0.1.0.dist-info/METADATA
dagster_dora-0.1.0.dist-info/WHEEL
dagster_dora-0.1.0.dist-info/RECORD
